hstream/__init__.py
hstream/__main__.py
hstream/cli.py
hstream/components/components.py
hstream/components/styling_components.py
hstream/django_server/hs/__init__.py
hstream/django_server/hs/apps.py
hstream/django_server/hs/session_utils.py
hstream/django_server/hs/urls.py
hstream/django_server/hs/views.py
hstream/django_server/manage.py
hstream/django_server/root/__init__.py
hstream/django_server/root/asgi.py
hstream/django_server/root/settings.py
hstream/django_server/root/urls.py
hstream/django_server/root/wsgi.py
hstream/hs.py
hstream/run.py
hstream/template.py
hstream/templates/error_html.html
hstream/templates/format_html.html
hstream/utils.py
hstream-0.1.57.dist-info/METADATA
hstream-0.1.57.dist-info/WHEEL
hstream-0.1.57.dist-info/entry_points.txt
hstream-0.1.57.dist-info/RECORD
