Metadata-Version: 2.3
Name: hstream
Version: 0.1.57
Summary: 
Author: Conrad
Author-email: conradbez1@gmail.com
Requires-Python: >=3.10,<4.0
Classifier: Programming Language :: Python :: 3
Classifier: Programming Language :: Python :: 3.10
Classifier: Programming Language :: Python :: 3.11
Classifier: Programming Language :: Python :: 3.12
Classifier: Programming Language :: Python :: 3.13
Requires-Dist: beautifulsoup4 (>=4.12,<5.0)
Requires-Dist: click (>=8.1.7,<9.0.0)
Requires-Dist: django (>=5.0.6,<6.0.0)
Requires-Dist: markdown (>=3.6,<4.0)
Requires-Dist: yattag (>=1.15.2,<2.0.0)
